{
  "schemaVersion" : 6,
  "version" : 17,
  "pipelineId" : "BronzeLayec39508a1-7dfa-4f34-8959-1b2a596efcb7",
  "title" : "BronzeLayerStreamHiveMetastore",
  "description" : "",
  "uuid" : "d1de249e-ed66-449f-97a5-2aced95fe714",
  "configuration" : [ {
    "name" : "executionMode",
    "value" : "STANDALONE"
  }, {
    "name" : "edgeHttpUrl",
    "value" : "http://localhost:18633"
  }, {
    "name" : "deliveryGuarantee",
    "value" : "AT_LEAST_ONCE"
  }, {
    "name" : "testOriginStage",
    "value" : "streamsets-datacollector-dev-lib::com_streamsets_pipeline_stage_devtest_rawdata_RawDataDSource::3"
  }, {
    "name" : "startEventStage",
    "value" : "streamsets-datacollector-basic-lib::com_streamsets_pipeline_stage_destination_devnull_ToErrorNullDTarget::1"
  }, {
    "name" : "stopEventStage",
    "value" : "streamsets-datacollector-basic-lib::com_streamsets_pipeline_stage_destination_devnull_ToErrorNullDTarget::1"
  }, {
    "name" : "shouldRetry",
    "value" : true
  }, {
    "name" : "triggerInterval",
    "value" : 2000
  }, {
    "name" : "retryAttempts",
    "value" : 3
  }, {
    "name" : "ludicrousMode",
    "value" : false
  }, {
    "name" : "ludicrousModeInputCount",
    "value" : false
  }, {
    "name" : "advancedErrorHandling",
    "value" : false
  }, {
    "name" : "notifyOnStates",
    "value" : [ "RUN_ERROR", "STOPPED", "FINISHED" ]
  }, {
    "name" : "emailIDs",
    "value" : [ ]
  }, {
    "name" : "constants",
    "value" : [ {
      "value" : "weather",
      "key" : "table_name_namevalue"
    }, {
      "key" : "database_name",
      "value" : "bronze"
    }, {
      "key" : "table_name",
      "value" : "tsource"
    } ]
  }, {
    "name" : "badRecordsHandling",
    "value" : "streamsets-datacollector-basic-lib::com_streamsets_pipeline_stage_destination_recordstolocalfilesystem_ToErrorLocalFSDTarget::1"
  }, {
    "name" : "errorRecordPolicy",
    "value" : "ORIGINAL_RECORD"
  }, {
    "name" : "statsAggregatorStage",
    "value" : "streamsets-datacollector-basic-lib::com_streamsets_pipeline_stage_destination_devnull_StatsDpmDirectlyDTarget::1"
  }, {
    "name" : "workerCount",
    "value" : 0
  }, {
    "name" : "clusterSlaveMemory",
    "value" : 2048
  }, {
    "name" : "clusterSlaveJavaOpts",
    "value" : "-XX:+UseConcMarkSweepGC -XX:+UseParNewGC -Dlog4j.debug"
  }, {
    "name" : "clusterLauncherEnv",
    "value" : [ ]
  }, {
    "name" : "mesosDispatcherURL",
    "value" : null
  }, {
    "name" : "logLevel",
    "value" : "INFO"
  }, {
    "name" : "hdfsS3ConfDir",
    "value" : null
  }, {
    "name" : "rateLimit",
    "value" : 1
  }, {
    "name" : "maxRunners",
    "value" : 0
  }, {
    "name" : "shouldCreateFailureSnapshot",
    "value" : true
  }, {
    "name" : "runnerIdleTIme",
    "value" : 60
  }, {
    "name" : "webhookConfigs",
    "value" : [ ]
  }, {
    "name" : "sparkConfigs",
    "value" : [ ]
  }, {
    "name" : "preprocessScript",
    "value" : "/*\nThe following script define a method\nthat increments an integer by 1 \nand registers it as a UDF with \nthe SparkSession, which can be accessed\nusing the variable named \"spark\":\ndef inc(i: Integer): Integer = {\n  i + 1\n}\nspark.udf.register (\"inc\", inc _)\n\n*/"
  }, {
    "name" : "clusterConfig.clusterType",
    "value" : "LOCAL"
  }, {
    "name" : "clusterConfig.sparkMasterUrl",
    "value" : "local[*]"
  }, {
    "name" : "clusterConfig.deployMode",
    "value" : "CLIENT"
  }, {
    "name" : "clusterConfig.hadoopUserName",
    "value" : null
  }, {
    "name" : "clusterConfig.sparkAppName",
    "value" : "${pipeline:title()}"
  }, {
    "name" : "clusterConfig.stagingDir",
    "value" : "/streamsets"
  }, {
    "name" : "clusterConfig.useYarnKerberosKeytab",
    "value" : false
  }, {
    "name" : "clusterConfig.yarnKerberosKeytabSource",
    "value" : "PROPERTIES_FILE"
  }, {
    "name" : "clusterConfig.yarnKerberosKeytab",
    "value" : null
  }, {
    "name" : "clusterConfig.yarnKerberosPrincipal",
    "value" : "name@DOMAIN"
  }, {
    "name" : "clusterConfig.callbackUrl",
    "value" : null
  }, {
    "name" : "databricksConfig.baseUrl",
    "value" : null
  }, {
    "name" : "databricksConfig.credentialType",
    "value" : null
  }, {
    "name" : "databricksConfig.username",
    "value" : null
  }, {
    "name" : "databricksConfig.password",
    "value" : null
  }, {
    "name" : "databricksConfig.token",
    "value" : null
  }, {
    "name" : "databricksConfig.provisionNewCluster",
    "value" : true
  }, {
    "name" : "databricksConfig.clusterId",
    "value" : null
  }, {
    "name" : "databricksConfig.clusterConfig",
    "value" : "{\n    \"num_workers\": 8,\n    \"spark_version\": \"5.3.x-scala2.11\",\n    \"node_type_id\": \"i3.xlarge\"\n}"
  }, {
    "name" : "databricksConfig.terminateCluster",
    "value" : false
  }, {
    "name" : "livyConfig.baseUrl",
    "value" : "https://localhost:30443/gateway/default/livy/v1/"
  }, {
    "name" : "livyConfig.username",
    "value" : null
  }, {
    "name" : "livyConfig.password",
    "value" : null
  }, {
    "name" : "amazonEMRConfig.userRegion",
    "value" : null
  }, {
    "name" : "amazonEMRConfig.userRegionCustom",
    "value" : null
  }, {
    "name" : "amazonEMRConfig.accessKey",
    "value" : null
  }, {
    "name" : "amazonEMRConfig.secretKey",
    "value" : null
  }, {
    "name" : "amazonEMRConfig.s3StagingUri",
    "value" : null
  }, {
    "name" : "amazonEMRConfig.provisionNewCluster",
    "value" : false
  }, {
    "name" : "amazonEMRConfig.clusterId",
    "value" : null
  }, {
    "name" : "amazonEMRConfig.clusterPrefix",
    "value" : null
  }, {
    "name" : "amazonEMRConfig.terminateCluster",
    "value" : false
  }, {
    "name" : "amazonEMRConfig.loggingEnabled",
    "value" : true
  }, {
    "name" : "amazonEMRConfig.s3LogUri",
    "value" : null
  }, {
    "name" : "amazonEMRConfig.enableEMRDebugging",
    "value" : true
  }, {
    "name" : "amazonEMRConfig.serviceRole",
    "value" : "EMR_DefaultRole"
  }, {
    "name" : "amazonEMRConfig.jobFlowRole",
    "value" : "EMR_EC2_DefaultRole"
  }, {
    "name" : "amazonEMRConfig.visibleToAllUsers",
    "value" : true
  }, {
    "name" : "amazonEMRConfig.ec2SubnetId",
    "value" : null
  }, {
    "name" : "amazonEMRConfig.masterSecurityGroup",
    "value" : null
  }, {
    "name" : "amazonEMRConfig.slaveSecurityGroup",
    "value" : null
  }, {
    "name" : "amazonEMRConfig.instanceCount",
    "value" : 2
  }, {
    "name" : "amazonEMRConfig.masterInstanceType",
    "value" : null
  }, {
    "name" : "amazonEMRConfig.masterInstanceTypeCustom",
    "value" : null
  }, {
    "name" : "amazonEMRConfig.slaveInstanceType",
    "value" : null
  }, {
    "name" : "amazonEMRConfig.slaveInstanceTypeCustom",
    "value" : null
  }, {
    "name" : "transformerEMRConfig.userRegion",
    "value" : null
  }, {
    "name" : "transformerEMRConfig.userRegionCustom",
    "value" : null
  }, {
    "name" : "transformerEMRConfig.useIAMRoles",
    "value" : false
  }, {
    "name" : "transformerEMRConfig.accessKey",
    "value" : null
  }, {
    "name" : "transformerEMRConfig.secretKey",
    "value" : null
  }, {
    "name" : "transformerEMRConfig.s3StagingUri",
    "value" : null
  }, {
    "name" : "transformerEMRConfig.provisionNewCluster",
    "value" : false
  }, {
    "name" : "transformerEMRConfig.clusterId",
    "value" : null
  }, {
    "name" : "transformerEMRConfig.emrVersion",
    "value" : null
  }, {
    "name" : "transformerEMRConfig.clusterPrefix",
    "value" : null
  }, {
    "name" : "transformerEMRConfig.terminateCluster",
    "value" : false
  }, {
    "name" : "transformerEMRConfig.loggingEnabled",
    "value" : true
  }, {
    "name" : "transformerEMRConfig.s3LogUri",
    "value" : null
  }, {
    "name" : "transformerEMRConfig.serviceRole",
    "value" : "EMR_DefaultRole"
  }, {
    "name" : "transformerEMRConfig.jobFlowRole",
    "value" : "EMR_EC2_DefaultRole"
  }, {
    "name" : "transformerEMRConfig.visibleToAllUsers",
    "value" : true
  }, {
    "name" : "transformerEMRConfig.ec2SubnetId",
    "value" : null
  }, {
    "name" : "transformerEMRConfig.masterSecurityGroup",
    "value" : null
  }, {
    "name" : "transformerEMRConfig.slaveSecurityGroup",
    "value" : null
  }, {
    "name" : "transformerEMRConfig.instanceCount",
    "value" : 2
  }, {
    "name" : "transformerEMRConfig.masterInstanceType",
    "value" : null
  }, {
    "name" : "transformerEMRConfig.masterInstanceTypeCustom",
    "value" : null
  }, {
    "name" : "transformerEMRConfig.slaveInstanceType",
    "value" : null
  }, {
    "name" : "transformerEMRConfig.slaveInstanceTypeCustom",
    "value" : null
  } ],
  "uiInfo" : {
    "previewConfig" : {
      "previewSource" : "CONFIGURED_SOURCE",
      "batchSize" : "5",
      "timeout" : 30000,
      "writeToDestinations" : true,
      "executeLifecycleEvents" : false,
      "showHeader" : true,
      "showFieldType" : true,
      "rememberMe" : true
    }
  },
  "fragments" : [ ],
  "stages" : [ {
    "instanceName" : "HTTPClient_01",
    "library" : "streamsets-datacollector-basic-lib",
    "stageName" : "com_streamsets_pipeline_stage_origin_http_HttpClientDSource",
    "stageVersion" : "15",
    "configuration" : [ {
      "name" : "conf.basic.maxBatchSize",
      "value" : 1000
    }, {
      "name" : "conf.basic.maxWaitTime",
      "value" : 2000
    }, {
      "name" : "conf.dataFormatConfig.compression",
      "value" : "NONE"
    }, {
      "name" : "conf.dataFormatConfig.filePatternInArchive",
      "value" : "*"
    }, {
      "name" : "conf.dataFormatConfig.charset",
      "value" : "UTF-8"
    }, {
      "name" : "conf.dataFormatConfig.removeCtrlChars",
      "value" : false
    }, {
      "name" : "conf.dataFormatConfig.textMaxLineLen",
      "value" : 65536
    }, {
      "name" : "conf.dataFormatConfig.useCustomDelimiter",
      "value" : false
    }, {
      "name" : "conf.dataFormatConfig.customDelimiter",
      "value" : "\\r\\n"
    }, {
      "name" : "conf.dataFormatConfig.includeCustomDelimiterInTheText",
      "value" : false
    }, {
      "name" : "conf.dataFormatConfig.jsonContent",
      "value" : "MULTIPLE_OBJECTS"
    }, {
      "name" : "conf.dataFormatConfig.jsonMaxObjectLen",
      "value" : 65535
    }, {
      "name" : "conf.dataFormatConfig.csvFileFormat",
      "value" : "CSV"
    }, {
      "name" : "conf.dataFormatConfig.csvHeader",
      "value" : "NO_HEADER"
    }, {
      "name" : "conf.dataFormatConfig.csvAllowExtraColumns",
      "value" : false
    }, {
      "name" : "conf.dataFormatConfig.csvExtraColumnPrefix",
      "value" : "_extra_"
    }, {
      "name" : "conf.dataFormatConfig.csvMaxObjectLen",
      "value" : 1024
    }, {
      "name" : "conf.dataFormatConfig.csvCustomDelimiter",
      "value" : "|"
    }, {
      "name" : "conf.dataFormatConfig.multiCharacterFieldDelimiter",
      "value" : "||"
    }, {
      "name" : "conf.dataFormatConfig.multiCharacterLineDelimiter",
      "value" : "${str:unescapeJava('\\\\n')}"
    }, {
      "name" : "conf.dataFormatConfig.csvCustomEscape",
      "value" : "\\"
    }, {
      "name" : "conf.dataFormatConfig.csvCustomQuote",
      "value" : "\""
    }, {
      "name" : "conf.dataFormatConfig.csvEnableComments",
      "value" : false
    }, {
      "name" : "conf.dataFormatConfig.csvCommentMarker",
      "value" : "#"
    }, {
      "name" : "conf.dataFormatConfig.csvIgnoreEmptyLines",
      "value" : true
    }, {
      "name" : "conf.dataFormatConfig.csvRecordType",
      "value" : "LIST_MAP"
    }, {
      "name" : "conf.dataFormatConfig.csvSkipStartLines",
      "value" : 0
    }, {
      "name" : "conf.dataFormatConfig.parseNull",
      "value" : false
    }, {
      "name" : "conf.dataFormatConfig.nullConstant",
      "value" : "\\\\N"
    }, {
      "name" : "conf.dataFormatConfig.xmlRecordElement",
      "value" : null
    }, {
      "name" : "conf.dataFormatConfig.preserveRootElement",
      "value" : true
    }, {
      "name" : "conf.dataFormatConfig.includeFieldXpathAttributes",
      "value" : false
    }, {
      "name" : "conf.dataFormatConfig.xPathNamespaceContext",
      "value" : [ ]
    }, {
      "name" : "conf.dataFormatConfig.outputFieldAttributes",
      "value" : false
    }, {
      "name" : "conf.dataFormatConfig.xmlMaxObjectLen",
      "value" : 4096
    }, {
      "name" : "conf.dataFormatConfig.logMode",
      "value" : "COMMON_LOG_FORMAT"
    }, {
      "name" : "conf.dataFormatConfig.logMaxObjectLen",
      "value" : 1024
    }, {
      "name" : "conf.dataFormatConfig.retainOriginalLine",
      "value" : false
    }, {
      "name" : "conf.dataFormatConfig.customLogFormat",
      "value" : "%h %l %u %t \"%r\" %>s %b"
    }, {
      "name" : "conf.dataFormatConfig.regex",
      "value" : "^(\\S+) (\\S+) (\\S+) \\[([\\w:/]+\\s[+\\-]\\d{4})\\] \"(\\S+) (\\S+) (\\S+)\" (\\d{3}) (\\d+)"
    }, {
      "name" : "conf.dataFormatConfig.fieldPathsToGroupName",
      "value" : [ {
        "fieldPath" : "/",
        "group" : 1
      } ]
    }, {
      "name" : "conf.dataFormatConfig.grokPatternDefinition",
      "value" : null
    }, {
      "name" : "conf.dataFormatConfig.grokPattern",
      "value" : "%{COMMONAPACHELOG}"
    }, {
      "name" : "conf.dataFormatConfig.onParseError",
      "value" : "ERROR"
    }, {
      "name" : "conf.dataFormatConfig.maxStackTraceLines",
      "value" : 50
    }, {
      "name" : "conf.dataFormatConfig.enableLog4jCustomLogFormat",
      "value" : false
    }, {
      "name" : "conf.dataFormatConfig.log4jCustomLogFormat",
      "value" : "%r [%t] %-5p %c %x - %m%n"
    }, {
      "name" : "conf.dataFormatConfig.avroSchemaSource",
      "value" : "SOURCE"
    }, {
      "name" : "conf.dataFormatConfig.avroSchema",
      "value" : null
    }, {
      "name" : "conf.dataFormatConfig.schemaRegistryUrls",
      "value" : [ ]
    }, {
      "name" : "conf.dataFormatConfig.basicAuth",
      "value" : null
    }, {
      "name" : "conf.dataFormatConfig.schemaLookupMode",
      "value" : "SUBJECT"
    }, {
      "name" : "conf.dataFormatConfig.subject",
      "value" : null
    }, {
      "name" : "conf.dataFormatConfig.schemaId",
      "value" : null
    }, {
      "name" : "conf.dataFormatConfig.avroSkipUnionIndex",
      "value" : false
    }, {
      "name" : "conf.dataFormatConfig.protoDescriptorFile",
      "value" : null
    }, {
      "name" : "conf.dataFormatConfig.messageType",
      "value" : null
    }, {
      "name" : "conf.dataFormatConfig.isDelimited",
      "value" : true
    }, {
      "name" : "conf.dataFormatConfig.binaryMaxObjectLen",
      "value" : 65535
    }, {
      "name" : "conf.dataFormatConfig.datagramMode",
      "value" : "SYSLOG"
    }, {
      "name" : "conf.dataFormatConfig.typesDbPath",
      "value" : null
    }, {
      "name" : "conf.dataFormatConfig.convertTime",
      "value" : false
    }, {
      "name" : "conf.dataFormatConfig.excludeInterval",
      "value" : true
    }, {
      "name" : "conf.dataFormatConfig.authFilePath",
      "value" : null
    }, {
      "name" : "conf.dataFormatConfig.netflowOutputValuesMode",
      "value" : "RAW_AND_INTERPRETED"
    }, {
      "name" : "conf.dataFormatConfig.maxTemplateCacheSize",
      "value" : -1
    }, {
      "name" : "conf.dataFormatConfig.templateCacheTimeoutMs",
      "value" : -1
    }, {
      "name" : "conf.dataFormatConfig.netflowOutputValuesModeDatagram",
      "value" : "RAW_AND_INTERPRETED"
    }, {
      "name" : "conf.dataFormatConfig.maxTemplateCacheSizeDatagram",
      "value" : -1
    }, {
      "name" : "conf.dataFormatConfig.templateCacheTimeoutMsDatagram",
      "value" : -1
    }, {
      "name" : "conf.dataFormatConfig.wholeFileMaxObjectLen",
      "value" : 8192
    }, {
      "name" : "conf.dataFormatConfig.rateLimit",
      "value" : "-1"
    }, {
      "name" : "conf.dataFormatConfig.verifyChecksum",
      "value" : false
    }, {
      "name" : "conf.dataFormatConfig.excelHeader",
      "value" : null
    }, {
      "name" : "conf.dataFormatConfig.excelSkipCellsWithNoHeader",
      "value" : false
    }, {
      "name" : "conf.dataFormatConfig.excelReadAllSheets",
      "value" : true
    }, {
      "name" : "conf.dataFormatConfig.excelSheetNames",
      "value" : [ ]
    }, {
      "name" : "conf.resourceUrl",
      "value" : "https://api.openweathermap.org/data/2.5/find?lat=46.4859841&lon=30.7249136&cnt=50&appid=d12dd3e0376f206595b3a0660911c2dc"
    }, {
      "name" : "conf.headers",
      "value" : [ ]
    }, {
      "name" : "conf.httpMethod",
      "value" : "GET"
    }, {
      "name" : "conf.timeZoneID",
      "value" : "Europe/Kiev"
    }, {
      "name" : "conf.requestBody",
      "value" : null
    }, {
      "name" : "conf.defaultRequestContentType",
      "value" : "application/json"
    }, {
      "name" : "conf.client.transferEncoding",
      "value" : "BUFFERED"
    }, {
      "name" : "conf.client.httpCompression",
      "value" : "NONE"
    }, {
      "name" : "conf.client.connectTimeoutMillis",
      "value" : 0
    }, {
      "name" : "conf.client.readTimeoutMillis",
      "value" : 0
    }, {
      "name" : "conf.client.authType",
      "value" : "NONE"
    }, {
      "name" : "conf.client.useOAuth2",
      "value" : false
    }, {
      "name" : "conf.client.oauth.consumerKey",
      "value" : null
    }, {
      "name" : "conf.client.oauth.consumerSecret",
      "value" : null
    }, {
      "name" : "conf.client.oauth.token",
      "value" : null
    }, {
      "name" : "conf.client.oauth.tokenSecret",
      "value" : null
    }, {
      "name" : "conf.client.oauth2.credentialsGrantType",
      "value" : null
    }, {
      "name" : "conf.client.oauth2.tokenUrl",
      "value" : null
    }, {
      "name" : "conf.client.oauth2.clientId",
      "value" : null
    }, {
      "name" : "conf.client.oauth2.clientSecret",
      "value" : null
    }, {
      "name" : "conf.client.oauth2.username",
      "value" : null
    }, {
      "name" : "conf.client.oauth2.password",
      "value" : null
    }, {
      "name" : "conf.client.oauth2.resourceOwnerClientId",
      "value" : null
    }, {
      "name" : "conf.client.oauth2.resourceOwnerClientSecret",
      "value" : null
    }, {
      "name" : "conf.client.oauth2.algorithm",
      "value" : "NONE"
    }, {
      "name" : "conf.client.oauth2.key",
      "value" : null
    }, {
      "name" : "conf.client.oauth2.jwtClaims",
      "value" : null
    }, {
      "name" : "conf.client.oauth2.transferEncoding",
      "value" : "BUFFERED"
    }, {
      "name" : "conf.client.oauth2.additionalValues",
      "value" : [ { } ]
    }, {
      "name" : "conf.client.basicAuth.username",
      "value" : null
    }, {
      "name" : "conf.client.basicAuth.password",
      "value" : null
    }, {
      "name" : "conf.client.useProxy",
      "value" : false
    }, {
      "name" : "conf.client.proxy.uri",
      "value" : null
    }, {
      "name" : "conf.client.proxy.username",
      "value" : null
    }, {
      "name" : "conf.client.proxy.password",
      "value" : null
    }, {
      "name" : "conf.client.tlsConfig.tlsEnabled",
      "value" : false
    }, {
      "name" : "conf.client.tlsConfig.keyStoreFilePath",
      "value" : null
    }, {
      "name" : "conf.client.tlsConfig.keyStoreType",
      "value" : "JKS"
    }, {
      "name" : "conf.client.tlsConfig.keyStorePassword",
      "value" : null
    }, {
      "name" : "conf.client.tlsConfig.keyStoreAlgorithm",
      "value" : "SunX509"
    }, {
      "name" : "conf.client.tlsConfig.trustStoreFilePath",
      "value" : null
    }, {
      "name" : "conf.client.tlsConfig.trustStoreType",
      "value" : "JKS"
    }, {
      "name" : "conf.client.tlsConfig.trustStorePassword",
      "value" : null
    }, {
      "name" : "conf.client.tlsConfig.trustStoreAlgorithm",
      "value" : "SunX509"
    }, {
      "name" : "conf.client.tlsConfig.useDefaultProtocols",
      "value" : true
    }, {
      "name" : "conf.client.tlsConfig.protocols",
      "value" : [ ]
    }, {
      "name" : "conf.client.tlsConfig.useDefaultCiperSuites",
      "value" : true
    }, {
      "name" : "conf.client.tlsConfig.cipherSuites",
      "value" : [ ]
    }, {
      "name" : "conf.client.requestLoggingConfig.enableRequestLogging",
      "value" : false
    }, {
      "name" : "conf.client.requestLoggingConfig.logLevel",
      "value" : "FINE"
    }, {
      "name" : "conf.client.requestLoggingConfig.verbosity",
      "value" : "HEADERS_ONLY"
    }, {
      "name" : "conf.client.requestLoggingConfig.maxEntitySize",
      "value" : 0
    }, {
      "name" : "conf.httpMode",
      "value" : "POLLING"
    }, {
      "name" : "conf.pollingInterval",
      "value" : 2000
    }, {
      "name" : "conf.dataFormat",
      "value" : "TEXT"
    }, {
      "name" : "conf.responseStatusActionConfigs",
      "value" : [ {
        "statusCode" : 500,
        "action" : "RETRY_EXPONENTIAL_BACKOFF",
        "backoffInterval" : 1000,
        "maxNumRetries" : 3
      } ]
    }, {
      "name" : "conf.responseTimeoutActionConfig.action",
      "value" : "RETRY_IMMEDIATELY"
    }, {
      "name" : "conf.responseTimeoutActionConfig.backoffInterval",
      "value" : 1000
    }, {
      "name" : "conf.responseTimeoutActionConfig.maxNumRetries",
      "value" : 10
    }, {
      "name" : "conf.pagination.mode",
      "value" : "NONE"
    }, {
      "name" : "conf.pagination.nextPageURLPrefix",
      "value" : null
    }, {
      "name" : "conf.pagination.nextPageFieldPath",
      "value" : null
    }, {
      "name" : "conf.pagination.stopCondition",
      "value" : null
    }, {
      "name" : "conf.pagination.startAt",
      "value" : null
    }, {
      "name" : "conf.pagination.resultFieldPath",
      "value" : null
    }, {
      "name" : "conf.pagination.keepAllFields",
      "value" : false
    }, {
      "name" : "conf.pagination.rateLimit",
      "value" : 2000
    }, {
      "name" : "stageOnRecordError",
      "value" : "TO_ERROR"
    } ],
    "uiInfo" : {
      "yPos" : 50,
      "stageType" : "SOURCE",
      "icon" : "httpclient.png",
      "description" : "Extracts weather through rest api",
      "label" : "Source Extractor",
      "xPos" : 60
    },
    "inputLanes" : [ ],
    "outputLanes" : [ "HTTPClient_01OutputLane15852562706180" ],
    "eventLanes" : [ ],
    "services" : [ ]
  }, {
    "instanceName" : "ExpressionEvaluator_01",
    "library" : "streamsets-datacollector-basic-lib",
    "stageName" : "com_streamsets_pipeline_stage_processor_expression_ExpressionDProcessor",
    "stageVersion" : "2",
    "configuration" : [ {
      "name" : "expressionProcessorConfigs",
      "value" : [ {
        "fieldToSet" : "/times",
        "expression" : "${time:extractStringFromDateTZ(time:now(), \"Europe/Kiev\", \"yyyy-MM-dd-HH-mm-ss-SSS\")}"
      }, {
        "fieldToSet" : "/keypartition",
        "expression" : "${time:extractStringFromDateTZ(time:now(), \"Europe/Kiev\", \"yyyy-MM-dd-HH-mm\")}"
      }, {
        "fieldToSet" : "/name",
        "expression" : "${table_name_namevalue}"
      } ]
    }, {
      "name" : "headerAttributeConfigs",
      "value" : [ {
        "attributeToSet" : "database",
        "headerAttributeExpression" : "${database_name}"
      }, {
        "attributeToSet" : "table_name",
        "headerAttributeExpression" : "${table_name}${time:extractStringFromDateTZ(time:now(), \"Europe/Kiev\", \"yyyyMMddHHmm\")}"
      } ]
    }, {
      "name" : "fieldAttributeConfigs",
      "value" : [ ]
    }, {
      "name" : "stageOnRecordError",
      "value" : "TO_ERROR"
    }, {
      "name" : "stageRequiredFields",
      "value" : [ ]
    }, {
      "name" : "stageRecordPreconditions",
      "value" : [ ]
    } ],
    "uiInfo" : {
      "yPos" : 50,
      "stageType" : "PROCESSOR",
      "icon" : "expression.png",
      "description" : "Генерирует YYYY-MM-DD-HH для партицирования, поле name для определения источника и пр...",
      "label" : "Add fields and attributes Generator",
      "xPos" : 280
    },
    "inputLanes" : [ "HTTPClient_01OutputLane15852562706180" ],
    "outputLanes" : [ "ExpressionEvaluator_01OutputLane15860331692140" ],
    "eventLanes" : [ ],
    "services" : [ ]
  }, {
    "instanceName" : "FieldRemover_01",
    "library" : "streamsets-datacollector-basic-lib",
    "stageName" : "com_streamsets_pipeline_stage_processor_fieldfilter_FieldFilterDProcessor",
    "stageVersion" : "1",
    "configuration" : [ {
      "name" : "filterOperation",
      "value" : "KEEP"
    }, {
      "name" : "fields",
      "value" : [ "/text", "/name", "/times" ]
    }, {
      "name" : "constant",
      "value" : null
    }, {
      "name" : "stageRequiredFields",
      "value" : [ ]
    }, {
      "name" : "stageRecordPreconditions",
      "value" : [ ]
    } ],
    "uiInfo" : {
      "yPos" : 50,
      "stageType" : "PROCESSOR",
      "icon" : "filter.png",
      "description" : "",
      "label" : "Field Remover 1",
      "xPos" : 500
    },
    "inputLanes" : [ "ExpressionEvaluator_01OutputLane15860331692140" ],
    "outputLanes" : [ "FieldRemover_01OutputLane15863651495150" ],
    "eventLanes" : [ ],
    "services" : [ ]
  }, {
    "instanceName" : "SchemaGenerator_01",
    "library" : "streamsets-datacollector-basic-lib",
    "stageName" : "com_streamsets_pipeline_stage_processor_schemagen_SchemaGeneratorDProcessor",
    "stageVersion" : "1",
    "configuration" : [ {
      "name" : "config.schemaType",
      "value" : "AVRO"
    }, {
      "name" : "config.schemaName",
      "value" : "${table_name_namevalue}"
    }, {
      "name" : "config.attributeName",
      "value" : "avroSchema"
    }, {
      "name" : "config.avroNamespace",
      "value" : null
    }, {
      "name" : "config.avroDoc",
      "value" : null
    }, {
      "name" : "config.avroNullableFields",
      "value" : false
    }, {
      "name" : "config.avroDefaultNullable",
      "value" : true
    }, {
      "name" : "config.avroDefaultTypes",
      "value" : [ { } ]
    }, {
      "name" : "config.avroExpandTypes",
      "value" : false
    }, {
      "name" : "config.precisionAttribute",
      "value" : "precision"
    }, {
      "name" : "config.scaleAttribute",
      "value" : "scale"
    }, {
      "name" : "config.defaultPrecision",
      "value" : -1
    }, {
      "name" : "config.defaultScale",
      "value" : -1
    }, {
      "name" : "config.enableCache",
      "value" : false
    }, {
      "name" : "config.cacheSize",
      "value" : 50
    }, {
      "name" : "config.cacheKeyExpression",
      "value" : null
    }, {
      "name" : "stageOnRecordError",
      "value" : "TO_ERROR"
    }, {
      "name" : "stageRequiredFields",
      "value" : [ ]
    }, {
      "name" : "stageRecordPreconditions",
      "value" : [ ]
    } ],
    "uiInfo" : {
      "yPos" : 50,
      "stageType" : "PROCESSOR",
      "icon" : "schemagen.png",
      "description" : "",
      "label" : "Schema Generator 1",
      "xPos" : 720
    },
    "inputLanes" : [ "FieldRemover_01OutputLane15863651495150" ],
    "outputLanes" : [ "SchemaGenerator_01OutputLane15863609670300" ],
    "eventLanes" : [ ],
    "services" : [ ]
  }, {
    "instanceName" : "HiveMetadata_01",
    "library" : "streamsets-datacollector-cdh_5_7-lib",
    "stageName" : "com_streamsets_pipeline_stage_processor_hive_HiveMetadataDProcessor",
    "stageVersion" : "3",
    "configuration" : [ {
      "name" : "hiveConfigBean.hiveJDBCUrl",
      "value" : "jdbc:hive2://quickstart.cloudera:10000/${\"database.name\"}"
    }, {
      "name" : "hiveConfigBean.hiveJDBCDriver",
      "value" : "org.apache.hive.jdbc.HiveDriver"
    }, {
      "name" : "hiveConfigBean.useCredentials",
      "value" : false
    }, {
      "name" : "hiveConfigBean.username",
      "value" : null
    }, {
      "name" : "hiveConfigBean.password",
      "value" : null
    }, {
      "name" : "hiveConfigBean.driverProperties",
      "value" : [ { } ]
    }, {
      "name" : "hiveConfigBean.confDir",
      "value" : "/data/hive/conf"
    }, {
      "name" : "hiveConfigBean.additionalConfigProperties",
      "value" : [ ]
    }, {
      "name" : "hiveConfigBean.maxCacheSize",
      "value" : -1
    }, {
      "name" : "dbNameEL",
      "value" : "${record:attribute('database')}"
    }, {
      "name" : "tableNameEL",
      "value" : "${record:attribute('table_name')}"
    }, {
      "name" : "partitionList",
      "value" : [ ]
    }, {
      "name" : "externalTable",
      "value" : false
    }, {
      "name" : "tablePathTemplate",
      "value" : "/user/hive/warehouse/${record:attribute('database')}.db/${record:attribute('table_name')}"
    }, {
      "name" : "partitionPathTemplate",
      "value" : "dt=${record:attribute('dt')}"
    }, {
      "name" : "commentExpression",
      "value" : null
    }, {
      "name" : "decimalDefaultsConfig.scaleExpression",
      "value" : "${record:attribute(str:concat(str:concat('jdbc.', field:field()), '.scale'))}"
    }, {
      "name" : "decimalDefaultsConfig.precisionExpression",
      "value" : "${record:attribute(str:concat(str:concat('jdbc.', field:field()), '.precision'))}"
    }, {
      "name" : "timeDriver",
      "value" : "${time:now()}"
    }, {
      "name" : "timeZoneID",
      "value" : "UTC"
    }, {
      "name" : "convertTimesToString",
      "value" : false
    }, {
      "name" : "metadataHeaderAttributeConfigs",
      "value" : [ ]
    }, {
      "name" : "dataFormat",
      "value" : "AVRO"
    }, {
      "name" : "stageOnRecordError",
      "value" : "TO_ERROR"
    }, {
      "name" : "stageRequiredFields",
      "value" : [ ]
    }, {
      "name" : "stageRecordPreconditions",
      "value" : [ ]
    } ],
    "uiInfo" : {
      "outputStreamLabels" : [ "Data", "Metadata" ],
      "yPos" : 110,
      "stageType" : "PROCESSOR",
      "icon" : "metadata.png",
      "description" : "",
      "label" : "Hive Metadata 1",
      "xPos" : 938
    },
    "inputLanes" : [ "SchemaGenerator_01OutputLane15863609670300" ],
    "outputLanes" : [ "HiveMetadata_01OutputLane15863590295580", "HiveMetadata_01OutputLane15863590295581" ],
    "eventLanes" : [ ],
    "services" : [ ]
  }, {
    "instanceName" : "HadoopFS_01",
    "library" : "streamsets-datacollector-cdh_5_7-lib",
    "stageName" : "com_streamsets_pipeline_stage_destination_hdfs_HdfsDTarget",
    "stageVersion" : "5",
    "configuration" : [ {
      "name" : "hdfsTargetConfigBean.uniquePrefix",
      "value" : "sdc-${sdc:id()}"
    }, {
      "name" : "hdfsTargetConfigBean.fileNameSuffix",
      "value" : null
    }, {
      "name" : "hdfsTargetConfigBean.dirPathTemplateInHeader",
      "value" : false
    }, {
      "name" : "hdfsTargetConfigBean.dirPathTemplate",
      "value" : "/tmp/out/${YYYY()}-${MM()}-${DD()}-${hh()}"
    }, {
      "name" : "hdfsTargetConfigBean.timeZoneID",
      "value" : "UTC"
    }, {
      "name" : "hdfsTargetConfigBean.timeDriver",
      "value" : "${time:now()}"
    }, {
      "name" : "hdfsTargetConfigBean.maxRecordsPerFile",
      "value" : 0
    }, {
      "name" : "hdfsTargetConfigBean.maxFileSize",
      "value" : 0
    }, {
      "name" : "hdfsTargetConfigBean.idleTimeout",
      "value" : "${1 * HOURS}"
    }, {
      "name" : "hdfsTargetConfigBean.compression",
      "value" : "NONE"
    }, {
      "name" : "hdfsTargetConfigBean.otherCompression",
      "value" : null
    }, {
      "name" : "hdfsTargetConfigBean.fileType",
      "value" : "TEXT"
    }, {
      "name" : "hdfsTargetConfigBean.keyEl",
      "value" : "${uuid()}"
    }, {
      "name" : "hdfsTargetConfigBean.seqFileCompressionType",
      "value" : "BLOCK"
    }, {
      "name" : "hdfsTargetConfigBean.lateRecordsLimit",
      "value" : "${1 * HOURS}"
    }, {
      "name" : "hdfsTargetConfigBean.rollIfHeader",
      "value" : false
    }, {
      "name" : "hdfsTargetConfigBean.rollHeaderName",
      "value" : "roll"
    }, {
      "name" : "hdfsTargetConfigBean.lateRecordsAction",
      "value" : "SEND_TO_ERROR"
    }, {
      "name" : "hdfsTargetConfigBean.lateRecordsDirPathTemplate",
      "value" : "/tmp/late/${YYYY()}-${MM()}-${DD()}"
    }, {
      "name" : "hdfsTargetConfigBean.dataFormat",
      "value" : "AVRO"
    }, {
      "name" : "hdfsTargetConfigBean.hdfsPermissionCheck",
      "value" : true
    }, {
      "name" : "hdfsTargetConfigBean.permissionEL",
      "value" : null
    }, {
      "name" : "hdfsTargetConfigBean.skipOldTempFileRecovery",
      "value" : false
    }, {
      "name" : "hdfsTargetConfigBean.dataGeneratorFormatConfig.charset",
      "value" : "UTF-8"
    }, {
      "name" : "hdfsTargetConfigBean.dataGeneratorFormatConfig.csvFileFormat",
      "value" : "CSV"
    }, {
      "name" : "hdfsTargetConfigBean.dataGeneratorFormatConfig.csvHeader",
      "value" : "NO_HEADER"
    }, {
      "name" : "hdfsTargetConfigBean.dataGeneratorFormatConfig.csvReplaceNewLines",
      "value" : true
    }, {
      "name" : "hdfsTargetConfigBean.dataGeneratorFormatConfig.csvReplaceNewLinesString",
      "value" : " "
    }, {
      "name" : "hdfsTargetConfigBean.dataGeneratorFormatConfig.csvCustomDelimiter",
      "value" : "|"
    }, {
      "name" : "hdfsTargetConfigBean.dataGeneratorFormatConfig.csvCustomEscape",
      "value" : "\\"
    }, {
      "name" : "hdfsTargetConfigBean.dataGeneratorFormatConfig.csvCustomQuote",
      "value" : "\""
    }, {
      "name" : "hdfsTargetConfigBean.dataGeneratorFormatConfig.csvQuoteMode",
      "value" : "MINIMAL"
    }, {
      "name" : "hdfsTargetConfigBean.dataGeneratorFormatConfig.jsonMode",
      "value" : "MULTIPLE_OBJECTS"
    }, {
      "name" : "hdfsTargetConfigBean.dataGeneratorFormatConfig.textFieldPath",
      "value" : "/text"
    }, {
      "name" : "hdfsTargetConfigBean.dataGeneratorFormatConfig.textRecordSeparator",
      "value" : "\\n"
    }, {
      "name" : "hdfsTargetConfigBean.dataGeneratorFormatConfig.textFieldMissingAction",
      "value" : "ERROR"
    }, {
      "name" : "hdfsTargetConfigBean.dataGeneratorFormatConfig.textEmptyLineIfNull",
      "value" : false
    }, {
      "name" : "hdfsTargetConfigBean.dataGeneratorFormatConfig.avroSchemaSource",
      "value" : "HEADER"
    }, {
      "name" : "hdfsTargetConfigBean.dataGeneratorFormatConfig.avroSchema",
      "value" : null
    }, {
      "name" : "hdfsTargetConfigBean.dataGeneratorFormatConfig.registerSchema",
      "value" : false
    }, {
      "name" : "hdfsTargetConfigBean.dataGeneratorFormatConfig.schemaRegistryUrlsForRegistration",
      "value" : [ ]
    }, {
      "name" : "hdfsTargetConfigBean.dataGeneratorFormatConfig.schemaRegistryUrls",
      "value" : [ ]
    }, {
      "name" : "hdfsTargetConfigBean.dataGeneratorFormatConfig.basicAuthUserInfo",
      "value" : null
    }, {
      "name" : "hdfsTargetConfigBean.dataGeneratorFormatConfig.schemaLookupMode",
      "value" : "SUBJECT"
    }, {
      "name" : "hdfsTargetConfigBean.dataGeneratorFormatConfig.subject",
      "value" : null
    }, {
      "name" : "hdfsTargetConfigBean.dataGeneratorFormatConfig.subjectToRegister",
      "value" : null
    }, {
      "name" : "hdfsTargetConfigBean.dataGeneratorFormatConfig.basicAuthUserInfoForRegistration",
      "value" : null
    }, {
      "name" : "hdfsTargetConfigBean.dataGeneratorFormatConfig.schemaId",
      "value" : null
    }, {
      "name" : "hdfsTargetConfigBean.dataGeneratorFormatConfig.avroCompression",
      "value" : "NULL"
    }, {
      "name" : "hdfsTargetConfigBean.dataGeneratorFormatConfig.binaryFieldPath",
      "value" : "/"
    }, {
      "name" : "hdfsTargetConfigBean.dataGeneratorFormatConfig.protoDescriptorFile",
      "value" : null
    }, {
      "name" : "hdfsTargetConfigBean.dataGeneratorFormatConfig.messageType",
      "value" : null
    }, {
      "name" : "hdfsTargetConfigBean.dataGeneratorFormatConfig.fileNameEL",
      "value" : null
    }, {
      "name" : "hdfsTargetConfigBean.dataGeneratorFormatConfig.wholeFileExistsAction",
      "value" : "TO_ERROR"
    }, {
      "name" : "hdfsTargetConfigBean.dataGeneratorFormatConfig.includeChecksumInTheEvents",
      "value" : false
    }, {
      "name" : "hdfsTargetConfigBean.dataGeneratorFormatConfig.checksumAlgorithm",
      "value" : "MD5"
    }, {
      "name" : "hdfsTargetConfigBean.dataGeneratorFormatConfig.xmlPrettyPrint",
      "value" : true
    }, {
      "name" : "hdfsTargetConfigBean.dataGeneratorFormatConfig.xmlValidateSchema",
      "value" : false
    }, {
      "name" : "hdfsTargetConfigBean.dataGeneratorFormatConfig.xmlSchema",
      "value" : null
    }, {
      "name" : "hdfsTargetConfigBean.hdfsUri",
      "value" : "hdfs://quickstart.cloudera:8020"
    }, {
      "name" : "hdfsTargetConfigBean.hdfsUser",
      "value" : null
    }, {
      "name" : "hdfsTargetConfigBean.hdfsKerberos",
      "value" : false
    }, {
      "name" : "hdfsTargetConfigBean.hdfsConfDir",
      "value" : "/data/hive/conf"
    }, {
      "name" : "hdfsTargetConfigBean.hdfsConfigs",
      "value" : [ { } ]
    }, {
      "name" : "stageOnRecordError",
      "value" : "TO_ERROR"
    }, {
      "name" : "stageRequiredFields",
      "value" : [ ]
    }, {
      "name" : "stageRecordPreconditions",
      "value" : [ ]
    } ],
    "uiInfo" : {
      "yPos" : 170,
      "stageType" : "TARGET",
      "icon" : "hdfs.png",
      "description" : "",
      "label" : "Hadoop FS 1",
      "xPos" : 1160
    },
    "inputLanes" : [ "HiveMetadata_01OutputLane15863590295581" ],
    "outputLanes" : [ ],
    "eventLanes" : [ ],
    "services" : [ ]
  }, {
    "instanceName" : "HiveMetastore_01",
    "library" : "streamsets-datacollector-cdh_5_7-lib",
    "stageName" : "com_streamsets_pipeline_stage_destination_hive_HiveMetastoreDTarget",
    "stageVersion" : "2",
    "configuration" : [ {
      "name" : "conf.hiveConfigBean.hiveJDBCUrl",
      "value" : "jdbc:hive2://quickstart.cloudera:10000/${record:attribute('database')}"
    }, {
      "name" : "conf.hiveConfigBean.hiveJDBCDriver",
      "value" : "org.apache.hive.jdbc.HiveDriver"
    }, {
      "name" : "conf.hiveConfigBean.useCredentials",
      "value" : false
    }, {
      "name" : "conf.hiveConfigBean.username",
      "value" : null
    }, {
      "name" : "conf.hiveConfigBean.password",
      "value" : null
    }, {
      "name" : "conf.hiveConfigBean.driverProperties",
      "value" : [ { } ]
    }, {
      "name" : "conf.hiveConfigBean.confDir",
      "value" : "/data/hive/conf"
    }, {
      "name" : "conf.hiveConfigBean.additionalConfigProperties",
      "value" : [ ]
    }, {
      "name" : "conf.hiveConfigBean.maxCacheSize",
      "value" : -1
    }, {
      "name" : "conf.storedAsAvro",
      "value" : false
    }, {
      "name" : "conf.schemaFolderLocation",
      "value" : ".schemas"
    }, {
      "name" : "conf.hdfsUser",
      "value" : null
    }, {
      "name" : "conf.headerAttributeConfigs",
      "value" : [ ]
    }, {
      "name" : "stageOnRecordError",
      "value" : "TO_ERROR"
    }, {
      "name" : "stageRequiredFields",
      "value" : [ ]
    }, {
      "name" : "stageRecordPreconditions",
      "value" : [ ]
    } ],
    "uiInfo" : {
      "yPos" : 40,
      "stageType" : "TARGET",
      "icon" : "hive.png",
      "description" : "",
      "label" : "Hive Metastore 1",
      "xPos" : 1160
    },
    "inputLanes" : [ "HiveMetadata_01OutputLane15863590295580" ],
    "outputLanes" : [ ],
    "eventLanes" : [ ],
    "services" : [ ]
  } ],
  "errorStage" : {
    "instanceName" : "WritetoFile_ErrorStage",
    "library" : "streamsets-datacollector-basic-lib",
    "stageName" : "com_streamsets_pipeline_stage_destination_recordstolocalfilesystem_ToErrorLocalFSDTarget",
    "stageVersion" : "1",
    "configuration" : [ {
      "name" : "directory",
      "value" : "/data/out"
    }, {
      "name" : "uniquePrefix",
      "value" : "sdc-${sdc:id()}"
    }, {
      "name" : "rotationIntervalSecs",
      "value" : "${1 * HOURS}"
    }, {
      "name" : "maxFileSizeMbs",
      "value" : 512
    } ],
    "uiInfo" : {
      "yPos" : 50,
      "stageType" : "TARGET",
      "icon" : "",
      "description" : "",
      "label" : "Error Records - Write to File",
      "xPos" : 500
    },
    "inputLanes" : [ ],
    "outputLanes" : [ ],
    "eventLanes" : [ ],
    "services" : [ ]
  },
  "info" : {
    "pipelineId" : "BronzeLayec39508a1-7dfa-4f34-8959-1b2a596efcb7",
    "title" : "BronzeLayerStreamHiveMetastore",
    "description" : "",
    "created" : 1586364125036,
    "lastModified" : 1586369494265,
    "creator" : "admin",
    "lastModifier" : "admin",
    "lastRev" : "0",
    "uuid" : "4763bc67-5952-4c7a-9506-124beee57f2f",
    "valid" : false,
    "metadata" : {
      "labels" : [ ]
    },
    "name" : "BronzeLayec39508a1-7dfa-4f34-8959-1b2a596efcb7",
    "sdcVersion" : "3.14.0",
    "sdcId" : "73c64506-6fa2-11ea-80c6-d162cc9dd014"
  },
  "metadata" : {
    "labels" : [ ]
  },
  "statsAggregatorStage" : {
    "instanceName" : "statsAggregatorStageInstance",
    "library" : "streamsets-datacollector-basic-lib",
    "stageName" : "com_streamsets_pipeline_stage_destination_devnull_StatsDpmDirectlyDTarget",
    "stageVersion" : "1",
    "configuration" : [ ],
    "uiInfo" : {
      "stageType" : "TARGET",
      "label" : "Stats Aggregator -Write Directly to Control Hub - statistics are not aggregated across Data Collectors"
    },
    "inputLanes" : [ ],
    "outputLanes" : [ ],
    "eventLanes" : [ ],
    "services" : [ ]
  },
  "startEventStages" : [ {
    "instanceName" : "Discard_StartEventStage",
    "library" : "streamsets-datacollector-basic-lib",
    "stageName" : "com_streamsets_pipeline_stage_destination_devnull_ToErrorNullDTarget",
    "stageVersion" : "1",
    "configuration" : [ ],
    "uiInfo" : {
      "yPos" : 50,
      "stageType" : "TARGET",
      "icon" : "",
      "description" : "",
      "label" : "Start Event - Discard",
      "xPos" : 280
    },
    "inputLanes" : [ ],
    "outputLanes" : [ ],
    "eventLanes" : [ ],
    "services" : [ ]
  } ],
  "stopEventStages" : [ {
    "instanceName" : "Discard_StopEventStage",
    "library" : "streamsets-datacollector-basic-lib",
    "stageName" : "com_streamsets_pipeline_stage_destination_devnull_ToErrorNullDTarget",
    "stageVersion" : "1",
    "configuration" : [ ],
    "uiInfo" : {
      "yPos" : 50,
      "stageType" : "TARGET",
      "icon" : "",
      "description" : "",
      "label" : "Stop Event - Discard",
      "xPos" : 280
    },
    "inputLanes" : [ ],
    "outputLanes" : [ ],
    "eventLanes" : [ ],
    "services" : [ ]
  } ],
  "testOriginStage" : {
    "instanceName" : "com_streamsets_pipeline_stage_devtest_rawdata_RawDataDSource_TestOriginStage",
    "library" : "streamsets-datacollector-dev-lib",
    "stageName" : "com_streamsets_pipeline_stage_devtest_rawdata_RawDataDSource",
    "stageVersion" : "3",
    "configuration" : [ {
      "name" : "rawData",
      "value" : "{\n  \"f1\": \"abc\",\n  \"f2\": \"xyz\",\n  \"f3\": \"lmn\"\n}"
    }, {
      "name" : "stopAfterFirstBatch",
      "value" : false
    }, {
      "name" : "eventData",
      "value" : null
    }, {
      "name" : "stageOnRecordError",
      "value" : "TO_ERROR"
    } ],
    "uiInfo" : {
      "stageType" : "SOURCE",
      "label" : "Test Origin - Dev Raw Data Source"
    },
    "inputLanes" : [ ],
    "outputLanes" : [ "com_streamsets_pipeline_stage_devtest_rawdata_RawDataDSource_TestOriginStageOutputLane1" ],
    "eventLanes" : [ ],
    "services" : [ {
      "service" : "com.streamsets.pipeline.api.service.dataformats.DataFormatParserService",
      "serviceVersion" : 2,
      "configuration" : [ {
        "name" : "displayFormats",
        "value" : "DELIMITED,JSON,LOG,SDC_JSON,TEXT,XML"
      }, {
        "name" : "dataFormat",
        "value" : "JSON"
      }, {
        "name" : "dataFormatConfig.compression",
        "value" : "NONE"
      }, {
        "name" : "dataFormatConfig.filePatternInArchive",
        "value" : "*"
      }, {
        "name" : "dataFormatConfig.charset",
        "value" : "UTF-8"
      }, {
        "name" : "dataFormatConfig.removeCtrlChars",
        "value" : false
      }, {
        "name" : "dataFormatConfig.textMaxLineLen",
        "value" : 1024
      }, {
        "name" : "dataFormatConfig.useCustomDelimiter",
        "value" : false
      }, {
        "name" : "dataFormatConfig.customDelimiter",
        "value" : "\\r\\n"
      }, {
        "name" : "dataFormatConfig.includeCustomDelimiterInTheText",
        "value" : false
      }, {
        "name" : "dataFormatConfig.jsonContent",
        "value" : "MULTIPLE_OBJECTS"
      }, {
        "name" : "dataFormatConfig.jsonMaxObjectLen",
        "value" : 4096
      }, {
        "name" : "dataFormatConfig.csvFileFormat",
        "value" : "CSV"
      }, {
        "name" : "dataFormatConfig.csvHeader",
        "value" : "NO_HEADER"
      }, {
        "name" : "dataFormatConfig.csvAllowExtraColumns",
        "value" : false
      }, {
        "name" : "dataFormatConfig.csvExtraColumnPrefix",
        "value" : "_extra_"
      }, {
        "name" : "dataFormatConfig.csvMaxObjectLen",
        "value" : 1024
      }, {
        "name" : "dataFormatConfig.csvCustomDelimiter",
        "value" : "|"
      }, {
        "name" : "dataFormatConfig.multiCharacterFieldDelimiter",
        "value" : "||"
      }, {
        "name" : "dataFormatConfig.multiCharacterLineDelimiter",
        "value" : "${str:unescapeJava('\\\\n')}"
      }, {
        "name" : "dataFormatConfig.csvCustomEscape",
        "value" : "\\"
      }, {
        "name" : "dataFormatConfig.csvCustomQuote",
        "value" : "\""
      }, {
        "name" : "dataFormatConfig.csvEnableComments",
        "value" : false
      }, {
        "name" : "dataFormatConfig.csvCommentMarker",
        "value" : "#"
      }, {
        "name" : "dataFormatConfig.csvIgnoreEmptyLines",
        "value" : false
      }, {
        "name" : "dataFormatConfig.csvRecordType",
        "value" : "LIST_MAP"
      }, {
        "name" : "dataFormatConfig.csvSkipStartLines",
        "value" : 0
      }, {
        "name" : "dataFormatConfig.parseNull",
        "value" : false
      }, {
        "name" : "dataFormatConfig.nullConstant",
        "value" : "\\\\N"
      }, {
        "name" : "dataFormatConfig.xmlRecordElement",
        "value" : null
      }, {
        "name" : "dataFormatConfig.preserveRootElement",
        "value" : false
      }, {
        "name" : "dataFormatConfig.includeFieldXpathAttributes",
        "value" : false
      }, {
        "name" : "dataFormatConfig.xPathNamespaceContext",
        "value" : [ ]
      }, {
        "name" : "dataFormatConfig.outputFieldAttributes",
        "value" : false
      }, {
        "name" : "dataFormatConfig.xmlMaxObjectLen",
        "value" : 4096
      }, {
        "name" : "dataFormatConfig.logMode",
        "value" : "COMMON_LOG_FORMAT"
      }, {
        "name" : "dataFormatConfig.logMaxObjectLen",
        "value" : 1024
      }, {
        "name" : "dataFormatConfig.retainOriginalLine",
        "value" : false
      }, {
        "name" : "dataFormatConfig.customLogFormat",
        "value" : "%h %l %u %t \"%r\" %>s %b"
      }, {
        "name" : "dataFormatConfig.regex",
        "value" : "^(\\S+) (\\S+) (\\S+) \\[([\\w:/]+\\s[+\\-]\\d{4})\\] \"(\\S+) (\\S+) (\\S+)\" (\\d{3}) (\\d+)"
      }, {
        "name" : "dataFormatConfig.fieldPathsToGroupName",
        "value" : [ {
          "fieldPath" : "/",
          "group" : 1
        } ]
      }, {
        "name" : "dataFormatConfig.grokPatternDefinition",
        "value" : null
      }, {
        "name" : "dataFormatConfig.grokPattern",
        "value" : "%{COMMONAPACHELOG}"
      }, {
        "name" : "dataFormatConfig.onParseError",
        "value" : "ERROR"
      }, {
        "name" : "dataFormatConfig.maxStackTraceLines",
        "value" : 50
      }, {
        "name" : "dataFormatConfig.enableLog4jCustomLogFormat",
        "value" : false
      }, {
        "name" : "dataFormatConfig.log4jCustomLogFormat",
        "value" : "%r [%t] %-5p %c %x - %m%n"
      }, {
        "name" : "dataFormatConfig.avroSchemaSource",
        "value" : null
      }, {
        "name" : "dataFormatConfig.avroSchema",
        "value" : null
      }, {
        "name" : "dataFormatConfig.schemaRegistryUrls",
        "value" : [ ]
      }, {
        "name" : "dataFormatConfig.basicAuth",
        "value" : null
      }, {
        "name" : "dataFormatConfig.schemaLookupMode",
        "value" : "SUBJECT"
      }, {
        "name" : "dataFormatConfig.subject",
        "value" : null
      }, {
        "name" : "dataFormatConfig.schemaId",
        "value" : null
      }, {
        "name" : "dataFormatConfig.avroSkipUnionIndex",
        "value" : false
      }, {
        "name" : "dataFormatConfig.protoDescriptorFile",
        "value" : null
      }, {
        "name" : "dataFormatConfig.messageType",
        "value" : null
      }, {
        "name" : "dataFormatConfig.isDelimited",
        "value" : false
      }, {
        "name" : "dataFormatConfig.binaryMaxObjectLen",
        "value" : 1024
      }, {
        "name" : "dataFormatConfig.datagramMode",
        "value" : "SYSLOG"
      }, {
        "name" : "dataFormatConfig.typesDbPath",
        "value" : null
      }, {
        "name" : "dataFormatConfig.convertTime",
        "value" : false
      }, {
        "name" : "dataFormatConfig.excludeInterval",
        "value" : false
      }, {
        "name" : "dataFormatConfig.authFilePath",
        "value" : null
      }, {
        "name" : "dataFormatConfig.netflowOutputValuesMode",
        "value" : "RAW_AND_INTERPRETED"
      }, {
        "name" : "dataFormatConfig.maxTemplateCacheSize",
        "value" : -1
      }, {
        "name" : "dataFormatConfig.templateCacheTimeoutMs",
        "value" : -1
      }, {
        "name" : "dataFormatConfig.netflowOutputValuesModeDatagram",
        "value" : "RAW_AND_INTERPRETED"
      }, {
        "name" : "dataFormatConfig.maxTemplateCacheSizeDatagram",
        "value" : -1
      }, {
        "name" : "dataFormatConfig.templateCacheTimeoutMsDatagram",
        "value" : -1
      }, {
        "name" : "dataFormatConfig.wholeFileMaxObjectLen",
        "value" : 8192
      }, {
        "name" : "dataFormatConfig.rateLimit",
        "value" : "-1"
      }, {
        "name" : "dataFormatConfig.verifyChecksum",
        "value" : false
      }, {
        "name" : "dataFormatConfig.excelHeader",
        "value" : null
      }, {
        "name" : "dataFormatConfig.excelSkipCellsWithNoHeader",
        "value" : false
      }, {
        "name" : "dataFormatConfig.excelReadAllSheets",
        "value" : false
      }, {
        "name" : "dataFormatConfig.excelSheetNames",
        "value" : [ ]
      } ]
    } ]
  },
  "valid" : false,
  "issues" : {
    "pipelineIssues" : [ ],
    "stageIssues" : {
      "HiveMetastore_01" : [ {
        "instanceName" : "HiveMetastore_01",
        "serviceName" : null,
        "level" : "STAGE_CONFIG",
        "configGroup" : "HIVE",
        "configName" : "conf.hiveConfigBean.hiveJDBCUrl",
        "message" : "CREATION_005 - Could not resolve implicit EL expression 'jdbc:hive2://quickstart.cloudera:10000/${record:attribute('database')}': com.streamsets.pipeline.api.el.ELEvalException: CTRCMN_0100 - Error evaluating expression jdbc:hive2://quickstart.cloudera:10000/${record:attribute('database')}: javax.servlet.jsp.el.ELException: No function is mapped to the name \"record:attribute\"",
        "count" : 1,
        "additionalInfo" : null,
        "antennaDoctorMessages" : null
      } ]
    },
    "issueCount" : 1
  },
  "previewable" : false
}